foxford/__init__.py
foxford/client.py
foxford/level.py
foxford/users.py
foxford/bases/baseitem.py
foxford/bases/baselevel.py
foxford/bases/baseuser.py
foxford/partials/partiallevel.py
foxford/partials/partialuser.py
foxford/utilities/exceptions.py
foxford/utilities/requests.py
foxford-1.4.dist-info/LICENSE
foxford-1.4.dist-info/METADATA
foxford-1.4.dist-info/WHEEL
foxford-1.4.dist-info/top_level.txt
foxford-1.4.dist-info/RECORD
