Metadata-Version: 2.1
Name: foxford
Version: 1.4
Summary: Modern object-oriented asynchronous Python wrapper for the Foxford's web API.
Author-email: FrostX <denialfrostiks589@gmail.com>
Project-URL: Homepage, https://github.com/frostx-official/foxford
Project-URL: Issues, https://github.com/frostx-official/foxford/issues
Classifier: Programming Language :: Python :: 3
Classifier: License :: OSI Approved :: MIT License
Classifier: Operating System :: OS Independent
Classifier: Framework :: AsyncIO
Classifier: Topic :: Internet :: WWW/HTTP :: Dynamic Content :: CGI Tools/Libraries
Classifier: Topic :: Software Development :: Libraries
Requires-Python: >=3.7
License-File: LICENSE
